Metadata-Version: 2.1
Name: drf-typed
Version: 0.3.0
Summary: Use type annotations for request validation and serializer fields in Django REST Framework
Home-page: https://github.com/rsinger86/drf-typed
Author: Robert Singer
Author-email: robertgsinger@gmail.com
License: MIT
Keywords: django rest type annotations automatic validation validate
Platform: UNKNOWN
Classifier: Development Status :: 4 - Beta
Classifier: License :: OSI Approved :: MIT License
Classifier: Programming Language :: Python :: 3.8
Classifier: Programming Language :: Python :: 3.9
Classifier: Programming Language :: Python :: 3.10
License-File: LICENSE
